easy_channels/__init__.py
easy_channels/middleware.py
easy_channels/consumers/__init__.py
easy_channels/consumers/json.py
django_easy_channels-0.0.1.dist-info/METADATA
django_easy_channels-0.0.1.dist-info/WHEEL
django_easy_channels-0.0.1.dist-info/top_level.txt
django_easy_channels-0.0.1.dist-info/RECORD
