Metadata-Version: 2.1
Name: django-easy-channels
Version: 0.0.1
Summary: Lightweight framework for quickly making socket consumers using Django and DjangoChannels.
Home-page: https://github.com/brenodega28/django_easy_channels
Author: Breno Gomes
Author-email: brenodega28@gmail.com
License: UNKNOWN
Platform: UNKNOWN
Classifier: Programming Language :: Python :: 3
Classifier: License :: OSI Approved :: MIT License
Classifier: Operating System :: OS Independent
Requires-Python: >=3.6
